asterix/__init__.py
asterix/base.py
asterix/generated.py
asterix/py.typed
libasterix-0.29.0.dist-info/licenses/LICENSE
libasterix-0.29.0.dist-info/METADATA
libasterix-0.29.0.dist-info/WHEEL
libasterix-0.29.0.dist-info/top_level.txt
libasterix-0.29.0.dist-info/RECORD
