Metadata-Version: 2.4
Name: libasterix
Version: 0.29.0
Summary: Asterix data processing library
Author-email: Zoran Bošnjak <zoran.bosnjak@via.si>
License-Expression: MIT
Project-URL: Homepage, https://github.com/zoranbosnjak/asterix-libs/tree/main/libs/python#readme
Project-URL: Bug Tracker, https://github.com/zoranbosnjak/asterix-libs/issues
Keywords: asterix,eurocontrol,radar
Classifier: Programming Language :: Python :: 3
Classifier: Operating System :: OS Independent
Requires-Python: >=3.8
License-File: LICENSE
Requires-Dist: typing_extensions; python_version < "3.10"
Dynamic: license-file
